biobambam_tool/__init__.py
biobambam_tool/__main__.py
biobambam_tool/main.py
biobambam_tool/tools/__init__.py
biobambam_tool/tools/bamfixmateinformation.py
biobambam_tool/tools/bamindex.py
biobambam_tool/tools/bammarkduplicates.py
biobambam_tool/tools/bammarkduplicates2.py
biobambam_tool/tools/bammdnm.py
biobambam_tool/tools/bammerge.py
biobambam_tool/tools/bamtofastq.py
biobambam_tool/tools/bamvalidate.py
biobambam_tool-0.25.dist-info/DESCRIPTION.rst
biobambam_tool-0.25.dist-info/METADATA
biobambam_tool-0.25.dist-info/RECORD
biobambam_tool-0.25.dist-info/WHEEL
biobambam_tool-0.25.dist-info/entry_points.txt
biobambam_tool-0.25.dist-info/metadata.json
biobambam_tool-0.25.dist-info/top_level.txt
